odoo/addons/product_pricelist_simulation/README.rst
odoo/addons/product_pricelist_simulation/__init__.py
odoo/addons/product_pricelist_simulation/__manifest__.py
odoo/addons/product_pricelist_simulation/i18n/es.po
odoo/addons/product_pricelist_simulation/i18n/it.po
odoo/addons/product_pricelist_simulation/i18n/product_pricelist_simulation.pot
odoo/addons/product_pricelist_simulation/models/__init__.py
odoo/addons/product_pricelist_simulation/models/pricelist.py
odoo/addons/product_pricelist_simulation/readme/CONTRIBUTORS.rst
odoo/addons/product_pricelist_simulation/readme/DESCRIPTION.rst
odoo/addons/product_pricelist_simulation/readme/USAGE.rst
odoo/addons/product_pricelist_simulation/static/description/icon.png
odoo/addons/product_pricelist_simulation/static/description/index.html
odoo/addons/product_pricelist_simulation/tests/__init__.py
odoo/addons/product_pricelist_simulation/tests/test_product_pricelist_simulation.py
odoo/addons/product_pricelist_simulation/views/pricelist_views.xml
odoo/addons/product_pricelist_simulation/views/product_views.xml
odoo/addons/product_pricelist_simulation/wizards/__init__.py
odoo/addons/product_pricelist_simulation/wizards/wizard_preview_pricelist.py
odoo/addons/product_pricelist_simulation/wizards/wizard_preview_pricelist_views.xml
odoo13_addon_product_pricelist_simulation-13.0.1.0.1.dev6.dist-info/METADATA
odoo13_addon_product_pricelist_simulation-13.0.1.0.1.dev6.dist-info/WHEEL
odoo13_addon_product_pricelist_simulation-13.0.1.0.1.dev6.dist-info/top_level.txt
odoo13_addon_product_pricelist_simulation-13.0.1.0.1.dev6.dist-info/RECORD
